latecript/__init__.py
latecript/latecript_app.py
latecript/latecript_app.tcss
latecript/services/__init__.py
latecript/services/pyaudio_handler.py
latecript/services/speechmatics_handler.py
latecript-0.1.5.dist-info/METADATA
latecript-0.1.5.dist-info/WHEEL
latecript-0.1.5.dist-info/entry_points.txt
latecript-0.1.5.dist-info/licenses/LICENSE
latecript-0.1.5.dist-info/RECORD
