Metadata-Version: 2.4
Name: latecript
Version: 0.1.5
Summary: Latecript: transcript and translate audio from you input audio devices in real-time using Speechmatics API.
Author: aelouass
License-File: LICENSE
Requires-Python: >=3.12
Requires-Dist: asyncio>=3.4.3
Requires-Dist: certifi>=2025.1.31
Requires-Dist: pip-system-certs>=4.0
Requires-Dist: pyaudio>=0.2.14
Requires-Dist: pydantic>=2.10.6
Requires-Dist: sounddevice>=0.5.1
Requires-Dist: soundfile>=0.13.1
Requires-Dist: speechmatics-python>=3.0.2
Requires-Dist: textual>=1.0.0
Requires-Dist: tqdm>=4.67.1
Provides-Extra: dev
Requires-Dist: ruff>=0.9.7; extra == 'dev'
